oceanwaves/__init__.py
oceanwaves/datawell.py
oceanwaves/oceanwaves.py
oceanwaves/plot.py
oceanwaves/spectral.py
oceanwaves/swan.py
oceanwaves/units.py
oceanwaves/utils.py
oceanwaves/wavedroid.py
oceanwaves-1.0.0rc6.dist-info/DESCRIPTION.rst
oceanwaves-1.0.0rc6.dist-info/METADATA
oceanwaves-1.0.0rc6.dist-info/RECORD
oceanwaves-1.0.0rc6.dist-info/WHEEL
oceanwaves-1.0.0rc6.dist-info/metadata.json
oceanwaves-1.0.0rc6.dist-info/top_level.txt
