Metadata-Version: 2.0
Name: oceanwaves
Version: 1.0.0rc6
Summary: A toolbox for ocean wave datasets
Home-page: http://oceanwaves.readthedocs.io/
Author: Bas Hoonhout
Author-email: bas.hoonhout@deltares.nl
License: MIT
Keywords: ocean waves oceanwaves swan waverider wavedroid xarray
Platform: UNKNOWN
Classifier: Development Status :: 4 - Beta
Classifier: Environment :: Console
Classifier: Intended Audience :: Developers
Classifier: Intended Audience :: Science/Research
Classifier: License :: OSI Approved :: MIT License
Classifier: Natural Language :: English
Classifier: Operating System :: MacOS :: MacOS X
Classifier: Operating System :: Microsoft :: Windows
Classifier: Operating System :: POSIX
Classifier: Operating System :: Unix
Classifier: Programming Language :: Python :: 2.7
Classifier: Programming Language :: Python :: 3
Classifier: Programming Language :: Python :: 3.2
Classifier: Programming Language :: Python :: 3.3
Classifier: Programming Language :: Python :: 3.4
Classifier: Programming Language :: Python :: 3.5
Classifier: Programming Language :: Python :: 3.6
Classifier: Programming Language :: Python :: 3.7
Classifier: Topic :: Scientific/Engineering :: Interface Engine/Protocol Translator
Classifier: Topic :: Scientific/Engineering :: Physics
Classifier: Topic :: Scientific/Engineering :: Visualization
Requires-Python: >=2.7, <4
Requires-Dist: docopt
Requires-Dist: numpy
Requires-Dist: scipy
Requires-Dist: xarray
